fastchat/__init__.py
fastchat/constants.py
fastchat/conversation.py
fastchat/utils.py
fastchat/data/__init__.py
fastchat/data/clean_sharegpt.py
fastchat/data/convert_alpaca.py
fastchat/data/extract_gpt4_only.py
fastchat/data/extract_single_round.py
fastchat/data/filter_wrong_format.py
fastchat/data/get_stats.py
fastchat/data/hardcoded_questions.py
fastchat/data/inspect_data.py
fastchat/data/merge.py
fastchat/data/optional_clean.py
fastchat/data/optional_replace.py
fastchat/data/prepare_all.py
fastchat/data/pretty_json.py
fastchat/data/sample.py
fastchat/data/split_long_conversation.py
fastchat/data/split_train_test.py
fastchat/llm_judge/clean_judgment.py
fastchat/llm_judge/common.py
fastchat/llm_judge/compute_agreement.py
fastchat/llm_judge/download_mt_bench_pregenerated.py
fastchat/llm_judge/gen_api_answer.py
fastchat/llm_judge/gen_judgment.py
fastchat/llm_judge/gen_model_answer.py
fastchat/llm_judge/qa_browser.py
fastchat/llm_judge/show_result.py
fastchat/model/__init__.py
fastchat/model/apply_delta.py
fastchat/model/apply_lora.py
fastchat/model/compression.py
fastchat/model/convert_fp16.py
fastchat/model/llama_condense_monkey_patch.py
fastchat/model/make_delta.py
fastchat/model/model_adapter.py
fastchat/model/model_chatglm.py
fastchat/model/model_codet5p.py
fastchat/model/model_exllama.py
fastchat/model/model_falcon.py
fastchat/model/model_registry.py
fastchat/model/model_xfastertransformer.py
fastchat/model/model_yuan2.py
fastchat/model/monkey_patch_non_inplace.py
fastchat/model/rwkv_model.py
fastchat/model/upload_hub.py
fastchat/modules/__init__.py
fastchat/modules/awq.py
fastchat/modules/exllama.py
fastchat/modules/gptq.py
fastchat/modules/xfastertransformer.py
fastchat/protocol/api_protocol.py
fastchat/protocol/openai_api_protocol.py
fastchat/serve/__init__.py
fastchat/serve/api_provider.py
fastchat/serve/base_model_worker.py
fastchat/serve/call_monitor.py
fastchat/serve/cli.py
fastchat/serve/controller.py
fastchat/serve/gradio_block_arena_anony.py
fschat-0.2.36.dist-info/LICENSE
fschat-0.2.36.dist-info/METADATA
fschat-0.2.36.dist-info/WHEEL
fschat-0.2.36.dist-info/top_level.txt
fschat-0.2.36.dist-info/RECORD
